monilog/__init__.py
monilog/log_generator.py
monilog/monitoring.py
monilog/parser.py
monilog/statistics.py
monilog/utils.py
monilog/bin/__init__.py
monilog/bin/run_log_generator.py
monilog/bin/run_monitoring.py
monilog-0.1.4.dist-info/LICENSE
monilog-0.1.4.dist-info/METADATA
monilog-0.1.4.dist-info/WHEEL
monilog-0.1.4.dist-info/entry_points.txt
monilog-0.1.4.dist-info/top_level.txt
monilog-0.1.4.dist-info/RECORD
