Metadata-Version: 2.1
Name: monilog
Version: 0.1.4
Summary: HTTP log monitoring
Home-page: https://tayciryahmed.github.io/monilog/
Author: Taycir Yahmed
Author-email: taycir.yahmed@gmail.com
License: MIT
Keywords: HTTP log monitoring
Platform: UNKNOWN
Classifier: Programming Language :: Python :: 3
Classifier: Operating System :: OS Independent
